cryptoConsole/__init__.py
cryptoConsole/cryptoCurses.py
cryptoConsole/cryptowatch.py
cryptoPie/Adafruit_CharLCD.py
cryptoPie/__init__.py
cryptoPie/cryptoPie.py
cryptoUtils/__init__.py
cryptoUtils/cryptoUtils.py
cryptoUtils/cwconfig.py
cryptowatch-0.0.11.dist-info/DESCRIPTION.rst
cryptowatch-0.0.11.dist-info/METADATA
cryptowatch-0.0.11.dist-info/RECORD
cryptowatch-0.0.11.dist-info/WHEEL
cryptowatch-0.0.11.dist-info/entry_points.txt
cryptowatch-0.0.11.dist-info/metadata.json
cryptowatch-0.0.11.dist-info/top_level.txt
utils/__init__.py
utils/cryptoUtils.py
utils/cwconfig.py
