Metadata-Version: 2.0
Name: cryptowatch
Version: 0.0.11
Summary: Track prices and account balances for multiple cryptocurrencies
Home-page: https://github.com/alexanderepstein/cryptowatch
Author: Alexander Epstein
Author-email: epsteina@wit.edu
License: MIT
Keywords: cryptocurrencies,monitor,rpi,console
Platform: UNKNOWN
Classifier: License :: OSI Approved :: MIT License
Classifier: Programming Language :: Python :: 3
Classifier: Programming Language :: Python :: 3.3
Classifier: Programming Language :: Python :: 3.4
Classifier: Programming Language :: Python :: 3.5
Classifier: Programming Language :: Python :: 3.6
Classifier: Programming Language :: Python :: Implementation :: PyPy
Requires-Dist: Adafruit-GPIO
Requires-Dist: colorclass
Requires-Dist: requests
Requires-Dist: terminaltables
